facial_skincare/__init__.py
facial_skincare/facialskin.py
facial_skincare_devices-0.0.1.dist-info/LICENSE
facial_skincare_devices-0.0.1.dist-info/METADATA
facial_skincare_devices-0.0.1.dist-info/WHEEL
facial_skincare_devices-0.0.1.dist-info/top_level.txt
facial_skincare_devices-0.0.1.dist-info/RECORD
