Metadata-Version: 2.1
Name: facial-skincare-devices
Version: 0.0.1
Summary: A small example package of facial skincare devices and beauty tools
Home-page: https://www.llskin.jp/
Author: Angelauy
Author-email: llskintech@gmail.com
License: UNKNOWN
Project-URL: Bug Tracker, https://www.llskin.jp/mio2
Platform: UNKNOWN
Classifier: Programming Language :: Python :: 3
Classifier: License :: OSI Approved :: MIT License
Classifier: Operating System :: OS Independent
Requires-Python: >=3.6
License-File: LICENSE
